ovnImage/LikelihoodGenerator.py
ovnImage/__init__.py
ovnImage/decorators.py
ovnImage/functions.py
ovnImage/images.py
ovnImage/masks.py
ovnImage/metrics.py
ovnImage/plots/InteractivePlot.py
ovnImage/plots/MultiPlot.py
ovnImage/plots/__init__.py
ovnImage/plots/confussion_matrix.py
ovnImage/plots/plots.py
ovnImage/plots/video.py
ovnImage-0.3.4.dist-info/LICENSE
ovnImage-0.3.4.dist-info/METADATA
ovnImage-0.3.4.dist-info/WHEEL
ovnImage-0.3.4.dist-info/top_level.txt
ovnImage-0.3.4.dist-info/RECORD
