Metadata-Version: 2.1
Name: ovnImage
Version: 0.3.4
Summary: Useful helper functions of image processing and machine learning
Home-page: UNKNOWN
Author: Miquel Miró Nicolau, Bernat Galmés Rubert, Dr. Gabriel Moyà Alcover
Author-email: miquelca32@gmail.com, bernat_galmes@hotmail.com, gabriel_moya@uib.es
License: MIT
Platform: UNKNOWN
Requires-Dist: scikit-learn
Requires-Dist: matplotlib
Requires-Dist: seaborn
Requires-Dist: pandas
Requires-Dist: numpy
Requires-Dist: scikit-image
Requires-Dist: opencv-python
